pygetdp/__about__.py
pygetdp/__init__.py
pygetdp/constraint.py
pygetdp/formulation.py
pygetdp/function.py
pygetdp/functionspace.py
pygetdp/getdp_object.py
pygetdp/group.py
pygetdp/helpers.py
pygetdp/integration.py
pygetdp/jacobian.py
pygetdp/postoperation.py
pygetdp/postprocessing.py
pygetdp/problem_definition.py
pygetdp/resolution.py
pygetdp/rendering/__init__.py
pygetdp/rendering/prolexer.py
pygetdp/rendering/prostyle.py
pygetdp/rendering/render.py
pygetdp-1.0.0.dist-info/LICENSE
pygetdp-1.0.0.dist-info/METADATA
pygetdp-1.0.0.dist-info/WHEEL
pygetdp-1.0.0.dist-info/entry_points.txt
pygetdp-1.0.0.dist-info/top_level.txt
pygetdp-1.0.0.dist-info/RECORD
