Metadata-Version: 2.1
Name: pygetdp
Version: 1.0.0
Summary: Python frontend for GetDP.
Home-page: https://gitlab.com/benvial/pygetdp
Author: Benjamin Vial
Author-email: benjamin.vial84@gmail.com
License: License :: OSI Approved :: MIT License
Project-URL: Documentation, https://benvial.gitlab.io/pygetdp/index.html
Platform: any
Classifier: Development Status :: 5 - Production/Stable
Classifier: License :: OSI Approved :: MIT License
Classifier: Intended Audience :: Science/Research
Classifier: Operating System :: OS Independent
Classifier: Programming Language :: Python
Classifier: Programming Language :: Python :: 3
Classifier: Topic :: Scientific/Engineering :: Mathematics
Requires-Python: >=3
Requires-Dist: pygments
Requires-Dist: pillow
Provides-Extra: doc
Requires-Dist: matplotlib ; extra == 'doc'
Provides-Extra: test
Requires-Dist: pytest-cov ; extra == 'test'
